dora_ugv/__init__.py
dora_ugv/main.py
dora_ugv-0.4.1.dist-info/METADATA
dora_ugv-0.4.1.dist-info/WHEEL
dora_ugv-0.4.1.dist-info/entry_points.txt
dora_ugv-0.4.1.dist-info/top_level.txt
dora_ugv-0.4.1.dist-info/RECORD
