Metadata-Version: 2.4
Name: dora-ugv
Version: 0.4.1
Summary: Dora Node for using Agilex UGV
Author-email: Haixuan Xavier Tao <tao.xavier@outlook.com>
License: MIT
Requires-Python: >=3.8
Requires-Dist: dora-rs>=0.3.9
